litstudy/__init__.py
litstudy/clean.py
litstudy/common.py
litstudy/continent.py
litstudy/network.py
litstudy/nlp.py
litstudy/plot.py
litstudy/stats.py
litstudy/stopwords.py
litstudy/types.py
litstudy/sources/__init__.py
litstudy/sources/arxiv.py
litstudy/sources/bibtex.py
litstudy/sources/crossref.py
litstudy/sources/dblp.py
litstudy/sources/ieee.py
litstudy/sources/ris.py
litstudy/sources/scopus.py
litstudy/sources/semanticscholar.py
litstudy/sources/springer.py
litstudy-1.0.4.dist-info/LICENSE
litstudy-1.0.4.dist-info/METADATA
litstudy-1.0.4.dist-info/WHEEL
litstudy-1.0.4.dist-info/top_level.txt
litstudy-1.0.4.dist-info/RECORD
