Metadata-Version: 2.1
Name: litstudy
Version: 1.0.4
Summary: Using the power of Python and Jupyter notebooks to automate analysis of scientific literature
Home-page: https://github.com/nlesc/litstudy
Author: Stijn Heldens
Author-email: s.heldens@esciencecenter.nl
License: Apache 2.0
Project-URL: Bug Tracker, https://github.com/nlesc/litstudy/issues
Platform: UNKNOWN
Requires-Python: >=3.7
Requires-Dist: bibtexparser
Requires-Dist: feedparser
Requires-Dist: gensim
Requires-Dist: matplotlib
Requires-Dist: networkx
Requires-Dist: numpy
Requires-Dist: pandas
Requires-Dist: pybliometrics
Requires-Dist: pyvis
Requires-Dist: requests
Requires-Dist: scikit-learn
Requires-Dist: seaborn
Requires-Dist: unidecode
Requires-Dist: wordcloud
Provides-Extra: doc
Requires-Dist: nbsphinx ; extra == 'doc'
Requires-Dist: sphinx-rtd-theme ; extra == 'doc'
Requires-Dist: wheel ; extra == 'doc'
